CHANGELOG.md
LICENSE
MANIFEST.in
README.md
VERSION
setup.py
src/__init__.py
src/bin/vault-cli
src/vault/__init__.py
src/vault/databag.py
src/vault/key.py
src/vault/storage.py
vaultlib.egg-info/PKG-INFO
vaultlib.egg-info/SOURCES.txt
vaultlib.egg-info/dependency_links.txt
vaultlib.egg-info/requires.txt
vaultlib.egg-info/top_level.txt