Metadata-Version: 1.0
Name: vaultlib
Version: 0.0.1
Summary: vault library.
Home-page: UNKNOWN
Author: Alex Ethier
Author-email: vault@fx-tools.com
License: The MIT License (MIT)
